Metadata-Version: 2.1
Name: fesnd-probability
Version: 1.2
Summary: Gaussian and Binomial distributions
Author: Adegbenga Festus
Author-email: festlove2007@yahoo.com
License: UNKNOWN
Platform: UNKNOWN
